odoo/addons/purchase_order_no_zero_price/README.rst
odoo/addons/purchase_order_no_zero_price/__init__.py
odoo/addons/purchase_order_no_zero_price/__manifest__.py
odoo/addons/purchase_order_no_zero_price/i18n/es.po
odoo/addons/purchase_order_no_zero_price/i18n/it.po
odoo/addons/purchase_order_no_zero_price/i18n/purchase_order_no_zero_price.pot
odoo/addons/purchase_order_no_zero_price/models/__init__.py
odoo/addons/purchase_order_no_zero_price/models/purchase_order_line.py
odoo/addons/purchase_order_no_zero_price/readme/CONTRIBUTORS.rst
odoo/addons/purchase_order_no_zero_price/readme/DESCRIPTION.rst
odoo/addons/purchase_order_no_zero_price/readme/USAGE.rst
odoo/addons/purchase_order_no_zero_price/static/description/icon.png
odoo/addons/purchase_order_no_zero_price/static/description/index.html
odoo/addons/purchase_order_no_zero_price/tests/__init__.py
odoo/addons/purchase_order_no_zero_price/tests/test_purchase_order_no_zero_price.py
odoo_addon_purchase_order_no_zero_price-16.0.1.0.1.dist-info/METADATA
odoo_addon_purchase_order_no_zero_price-16.0.1.0.1.dist-info/WHEEL
odoo_addon_purchase_order_no_zero_price-16.0.1.0.1.dist-info/top_level.txt
odoo_addon_purchase_order_no_zero_price-16.0.1.0.1.dist-info/RECORD
